azure/cognitiveservices/inkrecognizer/__init__.py
azure/cognitiveservices/inkrecognizer/_client.py
azure/cognitiveservices/inkrecognizer/_enums.py
azure/cognitiveservices/inkrecognizer/_ink_stroke.py
azure/cognitiveservices/inkrecognizer/_models.py
azure/cognitiveservices/inkrecognizer/_version.py
azure/cognitiveservices/inkrecognizer/aio/__init__.py
azure/cognitiveservices/inkrecognizer/aio/_client_async.py
azure_cognitiveservices_inkrecognizer-1.0.0b1.dist-info/METADATA
azure_cognitiveservices_inkrecognizer-1.0.0b1.dist-info/WHEEL
azure_cognitiveservices_inkrecognizer-1.0.0b1.dist-info/top_level.txt
azure_cognitiveservices_inkrecognizer-1.0.0b1.dist-info/RECORD
