Metadata-Version: 2.1
Name: azure-cognitiveservices-inkrecognizer
Version: 1.0.0b1
Summary: Microsoft Azure Ink Recognizer Library for Python
Home-page: https://github.com/Azure/azure-sdk-for-python/tree/master/sdk/cognitiveservices/azure-cognitiveservices-inkrecognizer
Author: Microsoft Corporation
Author-email: azpysdkhelp@microsoft.com
License: MIT License
Platform: UNKNOWN
Classifier: Development Status :: 4 - Beta
Classifier: Programming Language :: Python
Classifier: Programming Language :: Python :: 2
Classifier: Programming Language :: Python :: 2.7
Classifier: Programming Language :: Python :: 3
Classifier: Programming Language :: Python :: 3.5
Classifier: Programming Language :: Python :: 3.6
Classifier: Programming Language :: Python :: 3.7
Classifier: License :: OSI Approved :: MIT License
Requires-Dist: azure-core (<2.0.0,>=1.0.0b2)
Requires-Dist: azure-cognitiveservices-nspkg ; python_version<'3.0'
Requires-Dist: enum34 (>=1.0.4) ; python_version<'3.0'
